pymemri/__init__.py
pymemri/gitlab_api.py
pymemri/integrator_registry.py
pymemri/test_utils.py
pymemri/cert/gitlab.memri.io.pem
pymemri/client_simulator/__init__.py
pymemri/client_simulator/password_simulator.py
pymemri/client_simulator/qr_flow.py
pymemri/client_simulator/qr_server.py
pymemri/cvu/__init__.py
pymemri/cvu/utils.py
pymemri/cvu/definitions/password_auth.cvu
pymemri/cvu/definitions/qr_code_auth.cvu
pymemri/cvu/definitions/request_email.cvu
pymemri/data/__init__.py
pymemri/data/basic.py
pymemri/data/loader.py
pymemri/data/schema/__init__.py
pymemri/data/schema/_central_schema.py
pymemri/data/schema/dataset.py
pymemri/data/schema/itembase.py
pymemri/data/schema/photo.py
pymemri/data/schema/schema.py
pymemri/data/schema/utils.py
pymemri/examples/__init__.py
pymemri/examples/example_plugin.py
pymemri/examples/example_schema.py
pymemri/exporters/__init__.py
pymemri/exporters/exporters.py
pymemri/plugin/__init__.py
pymemri/plugin/cli.py
pymemri/plugin/constants.py
pymemri/plugin/listeners.py
pymemri/plugin/oauth_handler.py
pymemri/plugin/pluginbase.py
pymemri/plugin/states.py
pymemri/plugin/trigger_plugin_base.py
pymemri/plugin/authenticators/__init__.py
pymemri/plugin/authenticators/credentials.py
pymemri/plugin/authenticators/oauth.py
pymemri/pod/__init__.py
pymemri/pod/api.py
pymemri/pod/client.py
pymemri/pod/db.py
pymemri/pod/graphql_utils.py
pymemri/pod/utils.py
pymemri/template/__init__.py
pymemri/template/config.py
pymemri/template/formatter.py
pymemri/webserver/__init__.py
pymemri/webserver/helpers.py
pymemri/webserver/public_api.py
pymemri/webserver/qr_endpoints.py
pymemri/webserver/webserver.py
pymemri/webserver/models/__init__.py
pymemri/webserver/models/trigger.py
pymemri/webserver/template/images.html
pymemri/webserver/template/success.html
pymemri-0.1.2.dist-info/LICENSE.txt
pymemri-0.1.2.dist-info/METADATA
pymemri-0.1.2.dist-info/WHEEL
pymemri-0.1.2.dist-info/entry_points.txt
pymemri-0.1.2.dist-info/top_level.txt
pymemri-0.1.2.dist-info/RECORD
