Metadata-Version: 2.1
Name: pymemri
Version: 0.1.2
Summary: A python client for the memri Pod, and tools to create Plugins
Home-page: https://gitlab.memri.io/memri/pymemri
Author: Memri
Author-email: koen.vanderveen@polis.global
License: MPPL License
Keywords: memri privacy personal data client python
Classifier: Development Status :: 3 - Alpha
Classifier: Programming Language :: Python :: 3
License-File: LICENSE.txt
Requires-Dist: requests
Requires-Dist: fastscript
Requires-Dist: fastapi[all] (==0.78.0)
Requires-Dist: giturlparse (==0.10.0)
Requires-Dist: pillow (==8.4.0)
Requires-Dist: GitPython (==3.1.27)
Requires-Dist: jinja2 (==3.0.0)
Requires-Dist: loguru (~=0.6.0)
Requires-Dist: pydantic (==1.10.2)
Requires-Dist: numpy
Provides-Extra: dev
Requires-Dist: pytest ; extra == 'dev'
Requires-Dist: pytest-cov ; extra == 'dev'
Requires-Dist: pre-commit ; extra == 'dev'
Requires-Dist: twine (~=4.0) ; extra == 'dev'
Requires-Dist: pandas ; extra == 'dev'
